tensornn/__init__.py
tensornn/activation.py
tensornn/errors.py
tensornn/layers.py
tensornn/loss.py
tensornn/nn.py
tensornn/optimizers.py
tensornn/tensor.py
tensornn/utils.py
tensornn/learning/__init__.py
tensornn-0.0.2.dist-info/LICENSE
tensornn-0.0.2.dist-info/METADATA
tensornn-0.0.2.dist-info/WHEEL
tensornn-0.0.2.dist-info/top_level.txt
tensornn-0.0.2.dist-info/RECORD
