Metadata-Version: 2.1
Name: tensornn
Version: 0.0.2
Summary: Machine learning library made from scratch
Home-page: https://github.com/ArjunSahlot/TensorNN
Author: Arjun Sahlot
Author-email: iarjun.sahlot@gmail.com
License: GNU GPL v3
Keywords: Machine Learning
Platform: UNKNOWN
Classifier: Programming Language :: Python :: 3
Classifier: Intended Audience :: Developers
Classifier: Topic :: Software Development :: Build Tools
Classifier: License :: OSI Approved :: GNU General Public License v3 (GPLv3)
Classifier: Operating System :: OS Independent
Requires-Python: >=3
Requires-Dist: numpy
